[
    {
      "question": "Hvilken norsk by er kjent for sin buekorps-tradisjon?",
      "answer": "Bergen"
    },
    {
      "question": "Hva kalles den norske nasjonaldagen?",
      "answer": "17. mai"
    },
    {
      "question": "Hvilken norsk forfatter skrev 'Sult'?",
      "answer": "Knut Hamsun"
    },
    {
      "question": "Hva er det norske navnet på Northern Lights?",
      "answer": "Nordlys"
    },
    {
      "question": "Hvilket land donerte frihetsstatuen i Oslo?",
      "answer": "Frankrike"
    }
  ]
  